<xml src="s0203a-m128.xml">

<p rend="subhead"><pgroup id="m128"/><readunit id="m128">8. upakkilesasuttavaṇṇanā</readunit></p>

<p n="236"> <hi rend="bold">evaṃ</hi> <pb ed="V" n="4.0150"/><pb ed="P" n="4.0203"/> <hi rend="bold">me suta</hi>nti upakkilesasuttaṃ| tattha <hi rend="bold">etadavocā</hi>ti neva bhedādhippāyena na piyakamyatāya, atha khvāssa etadahosi – ‘‘ime bhikkhū <pb ed="M" n="4.0145"/> mama vacanaṃ gahetvā na oramissanti, buddhā ca nāma hitānukampakā, addhā nesaṃ bhagavā ekaṃ kāraṇaṃ kathessati, taṃ sutvā ete oramissanti, tato tesaṃ phāsuvihāro bhavissatī’’ti| tasmā etaṃ ‘‘idha, bhante’’tiādivacanamavoca| <hi rend="bold">mā bhaṇḍana</hi>ntiādīsu ‘‘akatthā’’ti pāṭhasesaṃ gahetvā ‘‘mā bhaṇḍanaṃ akatthā’’ti evaṃ attho daṭṭhabbo| <hi rend="bold">aññataro</hi>ti so kira bhikkhu bhagavato atthakāmo, ayaṃ kirassa adhippāyo – ‘‘ime bhikkhū kodhābhibhūtā satthu vacanaṃ na gaṇhanti, mā bhagavā ete ovadanto kilamī’’ti, tasmā evamāha|</p>

<p><hi rend="bold">piṇḍāya pāvisī</hi>ti na kevalaṃ pāvisi, yenapi janena na diṭṭho, so maṃ passatūtipi adhiṭṭhāsi| kimatthaṃ adhiṭṭhāsīti? tesaṃ bhikkhūnaṃ damanatthaṃ| bhagavā hi tadā piṇḍapātappaṭikkanto ‘‘puthusaddo samajano’’tiādigāthā bhāsitvā kosambito bālakaloṇakāragāmaṃ gato| tato pācīnavaṃsadāyaṃ, tato pālileyyakavanasaṇḍaṃ gantvā pālileyyahatthināgena upaṭṭhahiyamāno temāsaṃ vasi| nagaravāsinopi – ‘‘satthā vihāraṃ gato, gacchāma dhammassavanāyā’’ti gandhapupphahatthā vihāraṃ gantvā ‘‘kahaṃ, bhante, satthā’’ti pucchiṃsu| ‘‘kahaṃ tumhe satthāraṃ dakkhatha, satthā ‘ime bhikkhū samagge <pb ed="P" n="4.0204"/> karissāmī’ti āgato, samagge kātuṃ asakkonto nikkhamitvā gato’’ti| ‘‘mayaṃ satampi sahassampi datvā satthāraṃ ānetuṃ na sakkoma, so no ayācito sayameva āgato, mayaṃ ime bhikkhū nissāya satthu sammukhā dhammakathaṃ sotuṃ na labhimhā| ime satthāraṃ uddissa pabbajitā, tasmimpi sāmaggiṃ karonte samaggā na jātā, kassāññassa vacanaṃ karissanti| alaṃ na imesaṃ bhikkhā dātabbā’’ti sakalanagare daṇḍaṃ ṭhapayiṃsu| te punadivase sakalanagaraṃ piṇḍāya caritvā kaṭacchumattampi bhikkhaṃ alabhitvā vihāraṃ āgamaṃsu| upāsakāpi te puna āhaṃsu – ‘‘yāva satthāraṃ na khamāpetha, tāva vo tameva daṇḍakamma’’nti| te ‘‘satthāraṃ khamāpessāmā’’ti bhagavati sāvatthiyaṃ anuppatte <pb ed="V" n="4.0151"/> tattha agamaṃsu| satthā tesaṃ aṭṭhārasa bhedakaravatthūni desesīti ayamettha pāḷimuttakakathā|</p>

<p n="237"> idāni <hi rend="bold">puthusaddo</hi>tiādigāthāsu puthu mahāsaddo assāti <hi rend="bold">puthusaddo| samajano</hi>ti samāno ekasadiso jano, sabbovāyaṃ bhaṇḍanakārakajano <pb ed="M" n="4.0146"/> samantato saddaniccharaṇena puthusaddo ceva sadiso cāti vuttaṃ hoti| <hi rend="bold">na bālo koci maññathā</hi>ti tatra koci ekopi ahaṃ bāloti na maññati, sabbepi paṇḍitamāninoyeva| <hi rend="bold">nāññaṃ bhiyyo amaññaru</hi>nti koci ekopi ahaṃ bāloti na ca maññi, bhiyyo ca saṅghasmiṃ bhijjamāne aññampi ekaṃ ‘‘mayhaṃ kāraṇā saṅgho bhijjatī’’ti idaṃ kāraṇaṃ na maññīti attho|</p>

<p><hi rend="bold">parimuṭṭhā</hi>ti muṭṭhassatino| <hi rend="bold">vācāgocarabhāṇino</hi>ti rākārassa rassādeso kato; vācāgocarāva<pb ed="P" n="4.0205"/>, na satipaṭṭhānagocarā, bhāṇino ca, kathaṃ bhāṇino? <hi rend="bold">yāvicchanti mukhāyāmaṃ,</hi> yāva mukhaṃ pasāretuṃ icchanti, tāva pasāretvā bhāṇino, ekopi saṅghagāravena mukhasaṅkocanaṃ na karotīti attho| <hi rend="bold">yena nītā</hi>ti yena kalahena imaṃ nillajjabhāvaṃ nītā| <hi rend="bold">na taṃ vidū</hi> na taṃ jānanti ‘‘evaṃ sādīnavo aya’’nti|</p>

<p><hi rend="bold">ye ca taṃ upanayhantī</hi>ti taṃ akkocchi mantiādikaṃ ākāraṃ ye upanayhanti| <hi rend="bold">sanantano</hi>ti porāṇo|</p>

<p><hi rend="bold">pare</hi>ti paṇḍite ṭhapetvā tato aññe bhaṇḍanakārakā pare nāma| te ettha saṅghamajjhe kalahaṃ karontā ‘‘mayaṃ yamāmase upayamāma nassāma satataṃ samitaṃ maccusantikaṃ gacchāmā’’ti na jānanti| <hi rend="bold">ye ca tattha vijānantī</hi>ti ye ca tattha paṇḍitā ‘‘mayaṃ maccuno samīpaṃ gacchāmā’’ti vijānanti| <hi rend="bold">tato sammanti medhagā</hi>ti evañhi te jānantā yonisomanasikāraṃ uppādetvā medhagānaṃ kalahānaṃ vūpasamāya paṭipajjanti|</p>

<p><hi rend="bold">aṭṭhicchinnā</hi>ti ayaṃ gāthā jātake (jā. 1.9.16) āgatā, brahmadattañca dīghāvukumārañca sandhāya <pb ed="V" n="4.0152"/> vuttā| ayañhettha attho – tesampi tathā pavattaverānaṃ hoti saṅgati, kasmā <pb ed="P" n="4.0206"/> tumhākaṃ na hoti, yesaṃ vo neva mātāpitūnaṃ aṭṭhīni chinnāni, na pāṇā haṭā na gavāssadhanāni haṭānīti|</p>

<p><hi rend="bold">sace</hi> <pb ed="M" n="4.0147"/> <hi rend="bold">labhethā</hi>tiādigāthā paṇḍitasahāyassa ca bālasahāyassa ca vaṇṇāvaṇṇadīpanatthaṃ vuttā| <hi rend="bold">abhibhuyya sabbāni parissayānī</hi>ti pākaṭaparissaye ca paṭicchannaparissaye ca abhibhavitvā tena saddhiṃ attamano satimā careyyāti|</p>

<p><hi rend="bold">rājāva raṭṭhaṃ vijita</hi>nti yathā attano vijitaraṭṭhaṃ mahājanakarājā ca arindamamahārājā ca pahāya ekakā vicariṃsu, evaṃ vicareyyāti attho| <hi rend="bold">mātaṅgaraññeva nāgo</hi>ti mātaṅgo araññe nāgova| <hi rend="bold">mātaṅgo</hi>ti hatthi vuccati| <hi rend="bold">nāgo</hi>ti mahantādhivacanametaṃ| yathā hi mātuposako mātaṅganāgo araññe eko cari, na ca pāpāni akāsi, yathā ca pālileyyako, evaṃ eko care, na ca pāpāni kayirāti vuttaṃ hoti|</p>

<p n="238"> <hi rend="bold">bālakaloṇakāragāmo</hi>ti upāligahapatissa bhogagāmo| <hi rend="bold">tenupasaṅkamī</hi>ti kasmā upasaṅkami? gaṇe kirassa ādīnavaṃ disvā ekavihāriṃ bhikkhuṃ passitukāmatā udapādi, tasmā sītādīhi pīḷito uṇhādīni patthayamāno viya upasaṅkami| <hi rend="bold">dhammiyā kathāyā</hi>ti ekībhāve ānisaṃsappaṭisaṃyuttāya| yena <pb ed="P" n="4.0207"/> pācīnavaṃsadāyo, tattha kasmā upasaṅkami? kalahakārake kirassa diṭṭhādīnavattā samaggavāsino bhikkhū passitukāmatā udapādi, tasmā sītādīhi pīḷito uṇhādīni patthayamāno viya tattha upasaṅkami| <hi rend="bold">āyasmā ca anuruddho</hi>tiādi vuttanayameva|</p>

<p n="241"> <hi rend="bold">atthi pana vo</hi>ti pacchimapucchāya lokuttaradhammaṃ puccheyya| so pana therānaṃ natthi, tasmā taṃ pucchituṃ na yuttanti parikammobhāsaṃ pucchati| <hi rend="bold">obhāsañceva sañjānāmā</hi>ti parikammobhāsaṃ sañjānāma| <hi rend="bold">dassanañca rūpāna</hi>nti dibbacakkhunā rūpadassanañca sañjānāma| <hi rend="bold">tañca nimittaṃ nappaṭivijjhāmā</hi>ti tañca kāraṇaṃ na jānāma, yena no obhāso ca rūpadassanañca antaradhāyati|</p>

<p><hi rend="bold">taṃ kho pana vo anuruddhā nimittaṃ paṭivijjhitabba</hi>nti taṃ vo kāraṇaṃ jānitabbaṃ| <hi rend="bold">ahampi suda</hi>nti anuruddhā tumhe kiṃ na āḷulessanti, ahampi imehi ekādasahi upakkilesehi <pb ed="V" n="4.0153"/> āḷulitapubboti dassetuṃ imaṃ desanaṃ <pb ed="M" n="4.0148"/> ārabhi| <hi rend="bold">vicikicchā kho me</hi>tiādīsu mahāsattassa ālokaṃ vaḍḍhetvā dibbacakkhunā nānāvidhāni rūpāni disvā ‘‘idaṃ kho ki’’nti vicikicchā udapādi| <hi rend="bold">samādhi cavī</hi>ti parikammasamādhi cavi| <hi rend="bold">obhāso</hi>ti parikammobhāsopi antaradhāyi, dibbacakkhunāpi rūpaṃ na passi| <hi rend="bold">amanasikāro</hi>ti rūpāni passato vicikicchā uppajjati, idāni kiñci na manasikarissāmīti amanasikāro udapādi|</p>

<p><hi rend="bold">thinamiddha</hi>nti <pb ed="P" n="4.0208"/> kiñci amanasikarontassa thinamiddhaṃ udapādi|</p>

<p><hi rend="bold">chambhitatta</hi>nti himavantābhimukhaṃ ālokaṃ vaḍḍhetvā dānavarakkhasajagarādayo addasa, athassa chambhitattaṃ udapādi|</p>

<p><hi rend="bold">uppila</hi>nti ‘‘mayā diṭṭhabhayaṃ pakatiyā olokiyamānaṃ natthi| adiṭṭhe kiṃ nāma bhaya’’nti cintayato uppilāvitattaṃ udapādi| <hi rend="bold">sakidevā</hi>ti ekapayogeneva pañca nidhikumbhiyopi passeyya|</p>

<p><hi rend="bold">duṭṭhulla</hi>nti mayā vīriyaṃ gāḷhaṃ paggahitaṃ, tena me uppilaṃ uppannanti vīriyaṃ sithilamakāsi, tato kāyadaratho kāyaduṭṭhullaṃ kāyālasiyaṃ udapādi|</p>

<p><hi rend="bold">accāraddhavīriya</hi>nti mama vīriyaṃ sithilaṃ karoto duṭṭhullaṃ uppannanti puna vīriyaṃ paggaṇhato accāraddhavīriyaṃ udapādi| <hi rend="bold">patameyyā</hi>ti mareyya|</p>

<p><hi rend="bold">atilīnavīriya</hi>nti mama vīriyaṃ paggaṇhato evaṃ jātanti puna vīriyaṃ sithilaṃ karoto atilīnavīriyaṃ udapādi|</p>

<p><hi rend="bold">abhijappā</hi>ti devalokābhimukhaṃ ālokaṃ vaḍḍhetvā devasaṅghaṃ passato taṇhā udapādi|</p>

<p><hi rend="bold">nānattasaññā</hi>ti mayhaṃ ekajātikaṃ rūpaṃ manasikarontassa abhijappā uppannā, nānāvidharūpaṃ <pb ed="V" n="4.0154"/> manasi karissāmīti kālena devalokābhimukhaṃ kālena manussalokābhimukhaṃ vaḍḍhetvā nānāvidhāni rūpāni manasikaroto nānattasaññā udapādi|</p>

<p><hi rend="bold">atinijjhāyitatta</hi>nti mayhaṃ nānāvidhāni rūpāni manasikarontassa nānattasaññā udapādi, iṭṭhaṃ vā aniṭṭhaṃ <pb ed="P" n="4.0209"/> vā ekajātikameva manasi karissāmīti tathā manasikaroto atinijjhāyitattaṃ rūpānaṃ udapādi|</p>

<p n="243"> <hi rend="bold">obhāsanimittaṃ</hi> <pb ed="M" n="4.0149"/> <hi rend="bold">manasi karomī</hi>ti parikammobhāsameva manasi karomi| <hi rend="bold">na ca rūpāni passāmī</hi>ti dibbacakkhunā rūpāni na passāmi| <hi rend="bold">rūpanimittaṃ manasi karomī</hi>ti dibbacakkhunā visayarūpameva manasi karomi|</p>

<p><hi rend="bold">parittañceva obhāsa</hi>nti parittakaṭṭhāne obhāsaṃ| <hi rend="bold">parittāni ca rūpānī</hi>ti parittakaṭṭhāne rūpāni| vipariyāyena dutiyavāro veditabbo| <hi rend="bold">paritto samādhī</hi>ti parittako parikammobhāso, obhāsaparittatañhi sandhāya idha parikammasamādhi ‘‘paritto’’ti vutto| <hi rend="bold">parittaṃ me tasmiṃ samaye</hi>ti tasmiṃ samaye dibbacakkhupi parittakaṃ hoti| appamāṇavārepi eseva nayo|</p>

<p n="245"> <hi rend="bold">avitakkampi vicāramatta</hi>nti pañcakanaye dutiyajjhānasamādhiṃ| <hi rend="bold">avitakkampi avicāra</hi>nti catukkanayepi pañcakanayepi jhānattayasamādhiṃ| <hi rend="bold">sappītika</hi>nti dukatikajjhānasamādhiṃ| <hi rend="bold">nippītika</hi>nti dukajjhānasamādhiṃ| <hi rend="bold">sātasahagata</hi>nti tikacatukkajjhānasamādhiṃ| <hi rend="bold">upekkhāsahagata</hi>nti catukkanaye catutthajjhānasamādhiṃ pañcakanaye pañcamajjhānasamādhiṃ|</p>

<p>kadā pana bhagavā imaṃ tividhaṃ samādhiṃ bhāveti? mahābodhimūle nisinno pacchimayāme| bhagavato hi paṭhamamaggo paṭhamajjhāniko ahosi, dutiyādayo dutiyatatiyacatutthajjhānikā<pb ed="P" n="4.0210"/>| pañcakanaye pañcamajjhānassa maggo natthīti so lokiyo ahosīti lokiyalokuttaramissakaṃ sandhāyetaṃ vuttaṃ| sesaṃ sabbattha uttānamevāti|</p>

<p>papañcasūdaniyā majjhimanikāyaṭṭhakathāya</p>

<p rend="centre">upakkilesasuttavaṇṇanā niṭṭhitā|</p>

</xml>