<xml src="s0303a-s25.xml">

<div id="sn3_4" n="sn3_4" type="samyutta">
<head rend="chapter"><pgroup id="s25"/><readunit id="s25">4. okkantasaṃyuttaṃ</readunit></head>

<p rend="subhead">1-10. cakkhusuttādivaṇṇanā</p>

<p n="302-311"> okkantasaṃyutte <pb ed="V" n="2.0307"/> <hi rend="bold">adhimuccatī</hi>ti saddhādhimokkhaṃ paṭilabhati| <hi rend="bold">okkanto sammattaniyāma</hi>nti paviṭṭho ariyamaggaṃ| <hi rend="bold">abhabbo ca tāva kālaṃ kātu</hi>nti iminā uppanne magge phalassa anantarāyataṃ dīpeti| uppannasmiñhi magge phalassa antarāyakaraṇaṃ nāma natthi| tenevāha – ‘‘ayañca puggalo sotāpattiphalasacchikiriyāya paṭipanno assa, kappassa ca uḍḍayhanavelā assa, neva tāva kappo uḍḍayheyya, yāvāyaṃ puggalo na sotāpattiphalaṃ sacchikaroti, ayaṃ vuccati puggalo ṭhitakappī’’ti (pu. pa. 17)| <hi rend="bold">mattaso nijjhānaṃ khamantī</hi>ti pamāṇato olokanaṃ khamanti| sesaṃ sabbattha uttānamevāti|</p>

<p rend="centre">okkantasaṃyuttavaṇṇanā niṭṭhitā|</p>
</div>

</xml>